Workbook
Name APORTE_MENSAL: Plan1!$D$13
Name PATRIMONIO: Plan1!$D$16
Name QTD_ANOS: Plan1!$D$14
Name RENDIMENTO_CARTEIRA: Plan1!$D$9
Name SALARIO: Plan1!$D$8
Name SGT_INVESTIMENTO: Plan1!$D$10
Name TAXA_MENSAL: Plan1!$D$15

Sheet Plan1
B1: 🪙INVESTMENTS
B7: CONFIGURAÇÕES
B8: Salário | D8: 2277
B9: Rendimento carteira | D9: 0.006
B10: Sugestão de investimento | D10: =D8*30% -> 683.1
B12: INVESTIMENTO MENSAL
B13: Quanto investir por mês? | D13: 200
B14: Por quantos anos? | D14: 5
B15: Taxa de rendimento mensal? | D15: 0.01079
B16: Patrimônio acumulado? | D16: =FV(TAXA_MENSAL,QTD_ANOS*12,APORTE_MENSAL*-1) -> 16755.383
B17: Dividendos mensais? | D17: =PATRIMONIO*RENDIMENTO_CARTEIRA -> 100.5323
B19: CENÁRIOS | D19: DIVIDENDOS
A20: 2 | B20: Quanto em 2 anos? | C20: =FV($D$15,$A20*12,$D$13*-1) -> 5445.5255 | D20: =C20*RENDIMENTO_CARTEIRA -> 32.673153
A21: 5 | B21: Quanto em 5 anos? | C21: =FV($D$15,$A21*12,$D$13*-1) -> 16755.383 | D21: =C21*RENDIMENTO_CARTEIRA -> 100.5323
A22: 10 | B22: Quanto em 10 anos? | C22: =FV($D$15,$A22*12,$D$13*-1) -> 48656.843 | D22: =C22*RENDIMENTO_CARTEIRA -> 291.94106
A23: 20 | B23: Quanto em 20 anos? | C23: =FV($D$15,$A23*12,$D$13*-1) -> 225039.68 | D23: =C23*RENDIMENTO_CARTEIRA -> 1350.2381
A24: 30 | B24: Quanto em 30 anos? | C24: =FV($D$15,$A24*12,$D$13*-1) -> 864433.93 | D24: =C24*RENDIMENTO_CARTEIRA -> 5186.6036
B26: PERFIL | C26: CONSERVADOR
B27: VALOR APORTE MENSAL | C27: =APORTE_MENSAL -> 200
B29: TIPO FII | C29: PERCENTUAL SUGERIDO | D29: VALORES
B30: PAPEL | C30: =VLOOKUP($C$26&"-"&B30,Planilha1!A:D,4,FALSE) -> 0.3 | D30: =C30*$C$27 -> 60
B31: TIJOLO | C31: =VLOOKUP($C$26&"-"&B31,Planilha1!A:D,4,FALSE) -> 0.5 | D31: =C31*$C$27 -> 100
B32: HIBRIDOS | C32: =VLOOKUP($C$26&"-"&B32,Planilha1!A:D,4,FALSE) -> 0.1 | D32: =C32*$C$27 -> 20
B33: FOFs | C33: =VLOOKUP($C$26&"-"&B33,Planilha1!A:D,4,FALSE) -> 0.1 | D33: =C33*$C$27 -> 20
B34: DESENVOLVIMENTO | C34: =VLOOKUP($C$26&"-"&B34,Planilha1!A:D,4,FALSE) -> 0 | D34: =C34*$C$27 -> 0
B35: HOTELARIAS | C35: =VLOOKUP($C$26&"-"&B35,Planilha1!A:D,4,FALSE) -> 0 | D35: =C35*$C$27 -> 0
B36: VALOR TOTAL | D36: =SUM(D30:D35) -> 200

Sheet Planilha1
A4: CHAVE COMPOSTA | B4: PERFIL | C4: TIPO FII | D4: %
A5: =B5&"-"&C5 -> CONSERVADOR-PAPEL | B5: CONSERVADOR | C5: PAPEL | D5: 0.3
A6: =B6&"-"&C6 -> CONSERVADOR-TIJOLO | B6: CONSERVADOR | C6: TIJOLO | D6: 0.5
A7: =B7&"-"&C7 -> CONSERVADOR-HIBRIDOS | B7: CONSERVADOR | C7: HIBRIDOS | D7: 0.1
A8: =B8&"-"&C8 -> CONSERVADOR-FOFs | B8: CONSERVADOR | C8: FOFs | D8: 0.1
A9: =B9&"-"&C9 -> CONSERVADOR-DESENVOLVIMENTO | B9: CONSERVADOR | C9: DESENVOLVIMENTO | D9: 0
A10: =B10&"-"&C10 -> CONSERVADOR-HOTELARIAS | B10: CONSERVADOR | C10: HOTELARIAS | D10: 0
A11: =B11&"-"&C11 -> MODERADO-PAPEL | B11: MODERADO | C11: PAPEL | D11: 0.32
A12: =B12&"-"&C12 -> MODERADO-TIJOLO | B12: MODERADO | C12: TIJOLO | D12: 0.35
A13: =B13&"-"&C13 -> MODERADO-HIBRIDOS | B13: MODERADO | C13: HIBRIDOS | D13: 0.08
A14: =B14&"-"&C14 -> MODERADO-FOFs | B14: MODERADO | C14: FOFs | D14: 0.05
A15: =B15&"-"&C15 -> MODERADO-DESENVOLVIMENTO | B15: MODERADO | C15: DESENVOLVIMENTO | D15: 0.1
A16: =B16&"-"&C16 -> MODERADO-HOTELARIAS | B16: MODERADO | C16: HOTELARIAS | D16: 0
... A22: =B22&"-"&C22 -> AGRESSIVO-HOTELARIAS | B22: AGRESSIVO | C22: HOTELARIAS | D22: 0.1
